atoti_observability/__init__.py
atoti_observability/_plugin.py
atoti_observability/data/atoti-observability.jar
atoti_observability/py.typed
atoti_observability-0.8.14.dist-info/METADATA
atoti_observability-0.8.14.dist-info/WHEEL
atoti_observability-0.8.14.dist-info/entry_points.txt
atoti_observability-0.8.14.dist-info/RECORD
