Metadata-Version: 2.1
Name: atoti-observability
Version: 0.8.14
Summary: Experimental plugin providing observability of Atoti sessions
Home-page: https://www.atoti.io
License: Proprietary
Keywords: atoti,observability,logging,monitoring,tracing
Author: ActiveViam
Author-email: dev@atoti.io
Requires-Python: >=3.9
Classifier: Development Status :: 2 - Pre-Alpha
Classifier: License :: Free To Use But Restricted
Classifier: License :: Other/Proprietary License
Classifier: Operating System :: OS Independent
Classifier: Programming Language :: Java
Classifier: Programming Language :: Python :: 3
Classifier: Programming Language :: Python :: 3.9
Classifier: Programming Language :: Python :: 3.10
Classifier: Programming Language :: Python :: 3.11
Classifier: Programming Language :: Python :: 3.12
Classifier: Typing :: Typed
Requires-Dist: atoti-core (==0.8.14)
Requires-Dist: typing-extensions (>=4.6.1)
Project-URL: Bug Tracker, https://github.com/atoti/atoti/issues
